grokipedia_mcp/__init__.py
grokipedia_mcp/__main__.py
grokipedia_mcp/icon.png
grokipedia_mcp/server.py
grokipedia_mcp_fastmcp-0.2.3.dist-info/METADATA
grokipedia_mcp_fastmcp-0.2.3.dist-info/WHEEL
grokipedia_mcp_fastmcp-0.2.3.dist-info/entry_points.txt
grokipedia_mcp_fastmcp-0.2.3.dist-info/licenses/LICENSE
grokipedia_mcp_fastmcp-0.2.3.dist-info/RECORD
