Metadata-Version: 2.4
Name: grokipedia-mcp-fastmcp
Version: 0.2.3
Summary: MCP server for Grokipedia
Project-URL: Homepage, https://github.com/fastmcp-me/grokipedia-mcp#readme
Project-URL: Repository, https://github.com/fastmcp-me/grokipedia-mcp.git
Project-URL: Issues, https://github.com/fastmcp-me/grokipedia-mcp/issues
License: MIT License
License-File: LICENSE
Requires-Python: >=3.12
Requires-Dist: click>=8.0.0
Requires-Dist: grokipedia-api-sdk>=0.1.3
Requires-Dist: mcp>=1.19.0
Requires-Dist: starlette>=0.36.0
Requires-Dist: uvicorn>=0.27.0
